{
  "$schema": "https://developer.microsoft.com/json-schemas/fabric/item/report/definition/visualContainer/2.4.0/schema.json",
  "name": "3e99036255a4a5f482cf",
  "position": {
    "x": 340.16009596530489,
    "y": 224.88361899928489,
    "z": 0,
    "height": 306.14408636877437,
    "width": 470.55479941867173,
    "tabOrder": 0
  },
  "visual": {
    "visualType": "tableEx",
    "query": {
      "queryState": {
        "Values": {
          "projections": [
            {
              "field": {
                "Column": {
                  "Expression": {
                    "SourceRef": {
                      "Entity": "t1"
                    }
                  },
                  "Property": "col1"
                }
              },
              "queryRef": "t1.col1",
              "nativeQueryRef": "col1"
            },
            {
              "field": {
                "Aggregation": {
                  "Expression": {
                    "Column": {
                      "Expression": {
                        "SourceRef": {
                          "Entity": "t1"
                        }
                      },
                      "Property": "col2"
                    }
                  },
                  "Function": 5
                }
              },
              "queryRef": "t1.col2",
              "nativeQueryRef": "Count of col2"
            }
          ]
        }
      }
    },
    "drillFilterOtherVisuals": true
  },
  "filterConfig": {
    "filters": [
      {
        "name": "0ab7b019dfd1dab0f76e",
        "field": {
          "Column": {
            "Expression": {
              "SourceRef": {
                "Entity": "t1"
              }
            },
            "Property": "col1"
          }
        },
        "type": "Categorical"
      },
      {
        "name": "3035dccbaf7466b188d8",
        "field": {
          "Aggregation": {
            "Expression": {
              "Column": {
                "Expression": {
                  "SourceRef": {
                    "Entity": "t1"
                  }
                },
                "Property": "col2"
              }
            },
            "Function": 5
          }
        },
        "type": "Advanced"
      }
    ]
  }
}